factorama/__init__.pyi
factorama/_factorama.cpython-38-x86_64-linux-gnu.so
factorama/_factorama.pyi
factorama/_factorama.cpp
factorama/__init__.py
factorama-1.1.1.dist-info/WHEEL
factorama-1.1.1.dist-info/METADATA
factorama-1.1.1.dist-info/RECORD
factorama-1.1.1.dist-info/licenses/LICENSE.txt
lib64/libfactorama.a
lib64/cmake/factorama/factorama-config.cmake
lib64/cmake/factorama/factorama-config-version.cmake
lib64/cmake/factorama/factorama-targets-release.cmake
lib64/cmake/factorama/factorama-targets.cmake
include/factorama/plane_variable.hpp
include/factorama/pose_prior_factors.hpp
include/factorama/landmark_variable.hpp
include/factorama/inverse_range_bearing_factor.hpp
include/factorama/stopwatch.hpp
include/factorama/bearing_observation_factor_2d.hpp
include/factorama/sparse_optimizer.hpp
include/factorama/pose_2d_prior_factor.hpp
include/factorama/bearing_projection_factor_2d.hpp
include/factorama/generic_between_factor.hpp
include/factorama/random_utils.hpp
include/factorama/rotation_variable.hpp
include/factorama/pose_2d_variable.hpp
include/factorama/factor_graph.hpp
include/factorama/pose_variable.hpp
include/factorama/pose_between_factors.hpp
include/factorama/plane_factor.hpp
include/factorama/linear_velocity_factor.hpp
include/factorama/coordinate_transform_factor.hpp
include/factorama/pose_2d_between_factor.hpp
include/factorama/numerical_jacobian.hpp
include/factorama/generic_prior_factor.hpp
include/factorama/base_types.hpp
include/factorama/plane_prior_factor.hpp
include/factorama/rotation_prior_factor.hpp
include/factorama/range_bearing_factor_2d.hpp
include/factorama/kernels.hpp
include/factorama/generic_variable.hpp
include/factorama/bearing_observation_factor.hpp
include/factorama/inverse_range_variable.hpp
include/eigen3/signature_of_eigen3_matrix_library
include/eigen3/unsupported/Eigen/SpecialFunctions
include/eigen3/unsupported/Eigen/NumericalDiff
include/eigen3/unsupported/Eigen/Polynomials
include/eigen3/unsupported/Eigen/AlignedVector3
include/eigen3/unsupported/Eigen/SparseExtra
include/eigen3/unsupported/Eigen/AutoDiff
